LICENSE.txt
MANIFEST.in
README.md
setup.py
data/ncmpy.yaml.example
ncmpy/__init__.py
ncmpy/__main__.py
ncmpy/config.py
ncmpy/keysym.py
ncmpy/pane.py
ncmpy/thread.py
ncmpy/ttplyrics.py
ncmpy/util.py
ncmpy.egg-info/PKG-INFO
ncmpy.egg-info/SOURCES.txt
ncmpy.egg-info/dependency_links.txt
ncmpy.egg-info/entry_points.txt
ncmpy.egg-info/requires.txt
ncmpy.egg-info/top_level.txt