Metadata-Version: 2.1
Name: ncmpy
Version: 1.5.7
Summary: a curses mpd client;
Home-page: https://github.com/cykerway/ncmpy
Author: Cyker Way
Author-email: cykerway@example.com
License: UNKNOWN
Project-URL: Bug Reports, https://github.com/cykerway/ncmpy/issues
Project-URL: Source, https://github.com/cykerway/ncmpy/
Keywords: mpd music player
Platform: UNKNOWN
Classifier: Development Status :: 5 - Production/Stable
Classifier: Intended Audience :: End Users/Desktop
Classifier: Topic :: Multimedia
Classifier: License :: OSI Approved :: GNU General Public License v3 (GPLv3)
Classifier: Programming Language :: Python :: 3.6
Classifier: Programming Language :: Python :: 3.7
Classifier: Programming Language :: Python :: 3.8
Classifier: Programming Language :: Python :: 3.9
